apiqlient/__init__.py
apiqlient/application.py
apiqlient/router.py
ApiQlient-0.0.4.dist-info/LICENSE
ApiQlient-0.0.4.dist-info/METADATA
ApiQlient-0.0.4.dist-info/WHEEL
ApiQlient-0.0.4.dist-info/top_level.txt
ApiQlient-0.0.4.dist-info/RECORD
