Metadata-Version: 2.1
Name: ApiQlient
Version: 0.0.4
Summary: Quickly create REST clients
Author-email: Radoslaw Gryta <radek.gryta@gmail.com>
Project-URL: Homepage, https://github.com/rgryta/ApiQlient
Project-URL: Bug Tracker, https://github.com/rgryta/ApiQlient/issues
Keywords: rest,api,client,framework
Classifier: Operating System :: OS Independent
Classifier: Natural Language :: English
Classifier: Programming Language :: Python :: 3
Classifier: Programming Language :: Python :: 3.11
Classifier: Programming Language :: Python :: 3.12
Classifier: License :: OSI Approved :: MIT License
Classifier: Topic :: Internet :: WWW/HTTP
Classifier: Development Status :: 2 - Pre-Alpha
Classifier: Intended Audience :: Information Technology
Classifier: Intended Audience :: Developers
Requires-Python: >=3.11
License-File: LICENSE
Requires-Dist: starlette
Requires-Dist: yarl
Requires-Dist: aiohttp
Requires-Dist: urllib3
Provides-Extra: all
Requires-Dist: munch ; extra == 'all'
Requires-Dist: pydantic ; extra == 'all'
Requires-Dist: dataclass-wizard ; extra == 'all'
Provides-Extra: dev
Requires-Dist: staging ; extra == 'dev'
Requires-Dist: black ; extra == 'dev'
Requires-Dist: isort ; extra == 'dev'
Requires-Dist: noprint ; extra == 'dev'
Requires-Dist: pylint ; extra == 'dev'
Requires-Dist: bump-my-version ; extra == 'dev'
Requires-Dist: mock ; extra == 'dev'
Requires-Dist: pytest ; extra == 'dev'
Requires-Dist: pytest-sugar ; extra == 'dev'
Requires-Dist: pytest-xdist ; extra == 'dev'
Requires-Dist: pytest-asyncio ; extra == 'dev'
Requires-Dist: pytest-timeout ; extra == 'dev'
Requires-Dist: coverage[toml] ; extra == 'dev'
